golife/__init__.py
golife/__main__.py
golife/cli.py
golife/grid.py
golife/patterns.py
golife/patterns.toml
golife/views.py
golife-1.0.0.dist-info/LICENSE
golife-1.0.0.dist-info/METADATA
golife-1.0.0.dist-info/WHEEL
golife-1.0.0.dist-info/RECORD
